fluxpoint/README.md
fluxpoint/__main__.py
fluxpoint/changelog.md
fluxpoint-0.1.2.dist-info/WHEEL
fluxpoint-0.1.2.dist-info/METADATA
fluxpoint-0.1.2.dist-info/RECORD
