Metadata-Version: 2.1
Name: fluxpoint
Version: 0.1.2
Summary: A library for making interaction with the Fluxpoint API easy.
Author: kunosyn
Author-email: kunosyn@gmail.com
Requires-Python: >=3.8.0,<3.9
Classifier: Programming Language :: Python :: 3
Classifier: Programming Language :: Python :: 3.8
Requires-Dist: requests (>=2.27.1,<3.0.0)
